{
  "index_id": "EVIDENCE-SONNY-20260201-071644",
  "run_id": "RUN-SONNY-20260201-071614",
  "plan_id": "PLAN-SONNY-20260201-071614",
  "generated_at": "2026-02-01T07:16:44.192928Z",
  "base_path": "D:\\projects\\becca-kernel\\governance\\runs\\RUN-SONNY-20260201-071614",
  "summary": {
    "total_items": 11,
    "total_size_bytes": 40261,
    "by_type": {
      "secrets_findings": 4,
      "scan_profile": 2,
      "audit_trail": 3,
      "config_snapshot": 1,
      "log_extract": 1
    },
    "by_source_task": {
      "T001": 3,
      "T002": 8
    }
  },
  "evidence": [
    {
      "evidence_id": "E0001",
      "path": "bq_executor\\evidence\\SECRET_FINDINGS.json",
      "type": "secrets_findings",
      "format": "json",
      "description": "SECRET_FINDINGS from secrets_scanner",
      "source_task": "T001",
      "source_tool": "secrets_scanner",
      "generated_at": "2026-02-01T07:16:29.419315Z",
      "size_bytes": 453,
      "hash": "sha256:a1352ba0c2d8a07c5c79515438b89b0c34998875b91f6bc40d72dd4fdbe6ca46",
      "linked_risks": [],
      "retention": "run_lifetime"
    },
    {
      "evidence_id": "E0002",
      "path": "bq_executor\\evidence\\SECRET_FINDINGS.md",
      "type": "secrets_findings",
      "format": "md",
      "description": "SECRET_FINDINGS from secrets_scanner",
      "source_task": "T001",
      "source_tool": "secrets_scanner",
      "generated_at": "2026-02-01T07:16:29.419315Z",
      "size_bytes": 968,
      "hash": "sha256:b79a5d73436f222ee7168f80a1bd09491165a9b60451331ccd9b14e663240af8",
      "linked_risks": [],
      "retention": "run_lifetime"
    },
    {
      "evidence_id": "E0003",
      "path": "bq_executor\\evidence\\SCAN_PROFILE.json",
      "type": "scan_profile",
      "format": "json",
      "description": "SCAN_PROFILE from secrets_scanner",
      "source_task": "T001",
      "source_tool": "secrets_scanner",
      "generated_at": "2026-02-01T07:16:29.419315Z",
      "size_bytes": 804,
      "hash": "sha256:2c21961591cd35a942e9843d72b44931a798f3e8af74c09335c7d3bb6353f8a8",
      "linked_risks": [],
      "retention": "run_lifetime"
    },
    {
      "evidence_id": "E0004",
      "path": "tool_inspector\\evidence\\project_structure.json",
      "type": "audit_trail",
      "format": "json",
      "description": "project_structure from inspector",
      "source_task": "T002",
      "source_tool": "inspector",
      "generated_at": "2026-02-01T07:16:44.131851Z",
      "size_bytes": 3508,
      "hash": "sha256:83e06bf54c07aa48f5b430040001e2d8c87bbf5aacc860fad1b504f0cd33f8ea",
      "linked_risks": [],
      "retention": "run_lifetime"
    },
    {
      "evidence_id": "E0005",
      "path": "tool_inspector\\evidence\\grep_results.json",
      "type": "audit_trail",
      "format": "json",
      "description": "grep_results from inspector",
      "source_task": "T002",
      "source_tool": "inspector",
      "generated_at": "2026-02-01T07:16:44.131851Z",
      "size_bytes": 3795,
      "hash": "sha256:0ede3dfcebc0b12addc317f3362e25315620dc5a96c2a49e298765d84b51a820",
      "linked_risks": [],
      "retention": "run_lifetime"
    },
    {
      "evidence_id": "E0006",
      "path": "tool_inspector\\evidence\\config_files.json",
      "type": "config_snapshot",
      "format": "json",
      "description": "config_files from inspector",
      "source_task": "T002",
      "source_tool": "inspector",
      "generated_at": "2026-02-01T07:16:44.131851Z",
      "size_bytes": 1918,
      "hash": "sha256:24fcfc7e7ba2737516a92347748f6567ec1a8fed75c217e3749b10914dba6fdd",
      "linked_risks": [],
      "retention": "run_lifetime"
    },
    {
      "evidence_id": "E0007",
      "path": "tool_inspector\\evidence\\error_patterns.json",
      "type": "audit_trail",
      "format": "json",
      "description": "error_patterns from inspector",
      "source_task": "T002",
      "source_tool": "inspector",
      "generated_at": "2026-02-01T07:16:44.131851Z",
      "size_bytes": 15306,
      "hash": "sha256:d4f7ee1736816702f8864b18e317932e9615f12872504e13c1a49d042236c4d0",
      "linked_risks": [],
      "retention": "run_lifetime"
    },
    {
      "evidence_id": "E0008",
      "path": "tool_inspector\\evidence\\SECRET_FINDINGS.json",
      "type": "secrets_findings",
      "format": "json",
      "description": "SECRET_FINDINGS from inspector",
      "source_task": "T002",
      "source_tool": "inspector",
      "generated_at": "2026-02-01T07:16:44.131851Z",
      "size_bytes": 454,
      "hash": "sha256:2a599be4f9fb94e011b75ef7c9d8f3446732830419ca2bdce110dfdde09d3cdc",
      "linked_risks": [],
      "retention": "run_lifetime"
    },
    {
      "evidence_id": "E0009",
      "path": "tool_inspector\\evidence\\SECRET_FINDINGS.md",
      "type": "secrets_findings",
      "format": "md",
      "description": "SECRET_FINDINGS from inspector",
      "source_task": "T002",
      "source_tool": "inspector",
      "generated_at": "2026-02-01T07:16:44.131851Z",
      "size_bytes": 968,
      "hash": "sha256:69e357b41620b6444cbf595c72f8f8fe17d71517f005cc7fe7f6cf9f0d99cf9f",
      "linked_risks": [],
      "retention": "run_lifetime"
    },
    {
      "evidence_id": "E0010",
      "path": "tool_inspector\\evidence\\SCAN_PROFILE.json",
      "type": "scan_profile",
      "format": "json",
      "description": "SCAN_PROFILE from inspector",
      "source_task": "T002",
      "source_tool": "inspector",
      "generated_at": "2026-02-01T07:16:44.131851Z",
      "size_bytes": 804,
      "hash": "sha256:f4ebb883aea54c7c93f45cf53826578becf5b7fb5700111da33741b07d3e2ec7",
      "linked_risks": [],
      "retention": "run_lifetime"
    },
    {
      "evidence_id": "E0011",
      "path": "tool_inspector\\evidence\\audit_log.json",
      "type": "log_extract",
      "format": "json",
      "description": "audit_log from inspector",
      "source_task": "T002",
      "source_tool": "inspector",
      "generated_at": "2026-02-01T07:16:44.131851Z",
      "size_bytes": 11283,
      "hash": "sha256:5501683c7fc8a80b86f5f639360e00f327e381cb75b601da9a3da22d56208e5d",
      "linked_risks": [],
      "retention": "run_lifetime"
    }
  ]
}